kurral/__init__.py
kurral/agent_decorator.py
kurral/agent_replay.py
kurral/ars_scorer.py
kurral/artifact_generator.py
kurral/artifact_manager.py
kurral/cache.py
kurral/config.py
kurral/decorator.py
kurral/langchain_integration.py
kurral/replay_detector.py
kurral/replay_executor.py
kurral/side_effect_config.py
kurral/tool_stubber.py
kurral/cli/__init__.py
kurral/cli/agent_replay.py
kurral/cli/mcp_cmd.py
kurral/cli/replay_cmd.py
kurral/cli/security_cmd.py
kurral/database/__init__.py
kurral/database/connection.py
kurral/database/metadata_service.py
kurral/database/models.py
kurral/mcp/__init__.py
kurral/mcp/capture.py
kurral/mcp/config.py
kurral/mcp/models.py
kurral/mcp/platform_client.py
kurral/mcp/proxy.py
kurral/mcp/replay.py
kurral/mcp/router.py
kurral/models/__init__.py
kurral/models/kurral.py
kurral/quickstart/__init__.py
kurral/quickstart/generator.py
kurral/quickstart/templates/base/README.md.template
kurral/quickstart/templates/base/agent.py.template
kurral/quickstart/templates/base/requirements.txt.template
kurral/quickstart/templates/kurral_config/config.yaml.template
kurral/quickstart/templates/langchain/agent.py.template
kurral/quickstart/templates/langchain/requirements.txt.template
kurral/quickstart/templates/langchain/tools/__init__.py.template
kurral/quickstart/templates/langchain/tools/calculator.py.template
kurral/quickstart/templates/langchain/tools/file_system.py.template
kurral/quickstart/templates/langchain/tools/web_search.py.template
kurral/quickstart/templates/shared/README.md.template
kurral/quickstart/templates/shared/tests/test_agent.py.template
kurral/quickstart/templates/tests/test_agent.py.template
kurral/quickstart/templates/tools/__init__.py.template
kurral/quickstart/templates/tools/calculator.py.template
kurral/quickstart/templates/tools/file_system.py.template
kurral/quickstart/templates/tools/web_search.py.template
kurral/quickstart/templates/vanilla/agent.py.template
kurral/quickstart/templates/vanilla/requirements.txt.template
kurral-0.4.1.dist-info/METADATA
kurral-0.4.1.dist-info/WHEEL
kurral-0.4.1.dist-info/entry_points.txt
kurral-0.4.1.dist-info/top_level.txt
kurral-0.4.1.dist-info/RECORD
